setup.py
Soaldd/__init__.py
Soaldd/ebell.py
ebell.egg-info/PKG-INFO
ebell.egg-info/SOURCES.txt
ebell.egg-info/dependency_links.txt
ebell.egg-info/top_level.txt