Metadata-Version: 2.1
Name: ebell
Version: 0.1
Summary: telegram 
Author: Programmer king 
Classifier: Programming Language :: Python :: 3
Classifier: Operating System :: OS Independent
Classifier: License :: OSI Approved :: MIT License
